{
  "auth": {
    "user_pool_id": "us-east-1_LoTpMrtgh",
    "aws_region": "us-east-1",
    "user_pool_client_id": "5eg4a33vhgrgbfoshs8v5m0oon",
    "identity_pool_id": "us-east-1:dbab6a30-a378-42db-8b82-41aad0b3fab1",
    "mfa_methods": [],
    "standard_required_attributes": [
      "email"
    ],
    "username_attributes": [
      "email"
    ],
    "user_verification_types": [
      "email"
    ],
    "groups": [],
    "mfa_configuration": "NONE",
    "password_policy": {
      "min_length": 8,
      "require_lowercase": true,
      "require_numbers": true,
      "require_symbols": true,
      "require_uppercase": true
    },
    "unauthenticated_identities_enabled": true
  },
  "data": {
    "url": "https://h2gh3ng4fvacxdmkiuwfk2udmy.appsync-api.us-east-1.amazonaws.com/graphql",
    "aws_region": "us-east-1",
    "api_key": "da2-qyqhc2pxifbelgfhzhswqa7luy",
    "default_authorization_type": "API_KEY",
    "authorization_types": [
      "AMAZON_COGNITO_USER_POOLS",
      "AWS_IAM"
    ],
    "model_introspection": {
      "version": 1,
      "models": {},
      "enums": {},
      "nonModels": {
        "BedrockResponse": {
          "name": "BedrockResponse",
          "fields": {
            "body": {
              "name": "body",
              "isArray": false,
              "type": "String",
              "isRequired": false,
              "attributes": []
            },
            "error": {
              "name": "error",
              "isArray": false,
              "type": "String",
              "isRequired": false,
              "attributes": []
            }
          }
        }
      },
      "queries": {
        "askBedrock": {
          "name": "askBedrock",
          "isArray": false,
          "type": {
            "nonModel": "BedrockResponse"
          },
          "isRequired": false,
          "arguments": {
            "ingredients": {
              "name": "ingredients",
              "isArray": true,
              "type": "String",
              "isRequired": false,
              "isArrayNullable": true
            }
          }
        }
      }
    }
  },
  "version": "1.4"
}